intelliterm/__init__.py
intelliterm/chat.py
intelliterm/client.py
intelliterm/code.py
intelliterm/command_palette.py
intelliterm/config.py
intelliterm/console.py
intelliterm/constants.py
intelliterm/main.py
intelliterm/notifications.py
intelliterm/prompt.py
intelliterm/styling.py
intelliterm/types.py
intelliterm/utils.py
intelliterm-0.5.2.dist-info/LICENSE.txt
intelliterm-0.5.2.dist-info/METADATA
intelliterm-0.5.2.dist-info/WHEEL
intelliterm-0.5.2.dist-info/entry_points.txt
intelliterm-0.5.2.dist-info/RECORD
