Metadata-Version: 2.1
Name: intelliterm
Version: 0.5.2
Summary: Chat with AI from your terminal!
Home-page: https://github.com/ykrx/intelliterm
License: LICENSE.txt
Author: Yulian Kraynyak
Author-email: yulian@yulian.codes
Requires-Python: >=3.11,<4.0
Classifier: License :: Other/Proprietary License
Classifier: Programming Language :: Python :: 3
Classifier: Programming Language :: Python :: 3.11
Classifier: Programming Language :: Python :: 3.12
Requires-Dist: anthropic (>=0.23.1,<0.24.0)
Requires-Dist: openai (>=0.27.8,<0.28.0)
Requires-Dist: pick (>=2.2.0,<3.0.0)
Requires-Dist: platformdirs (>=3.8.0,<4.0.0)
Requires-Dist: prompt-toolkit (>=3.0.38,<4.0.0)
Requires-Dist: pyperclip (>=1.8.2,<2.0.0)
Requires-Dist: rich (>=13.4.2,<14.0.0)
Requires-Dist: setuptools (>=68.0.0,<69.0.0)
Requires-Dist: tiktoken (>=0.4.0,<0.5.0)
Project-URL: Repository, https://github.com/ykrx/intelliterm
